promtprof/__init__.py
promtprof/cli.py
promtprof/colors.py
promtprof/core.py
promtprof/fx.py
promtprof/models.py
promtprof-0.4.3.dist-info/licenses/LICENSE
promtprof-0.4.3.dist-info/METADATA
promtprof-0.4.3.dist-info/WHEEL
promtprof-0.4.3.dist-info/entry_points.txt
promtprof-0.4.3.dist-info/top_level.txt
promtprof-0.4.3.dist-info/RECORD
