Metadata-Version: 2.4
Name: promtprof
Version: 0.4.3
Summary: Prompt-Profiler & Token-Kostenrechner
Author-email: Maciej Rezler <hello@rezler.dev>
License: MIT
Requires-Python: >=3.9
License-File: LICENSE
Requires-Dist: PyYAML>=6
Provides-Extra: tiktoken
Requires-Dist: tiktoken>=0.7; extra == "tiktoken"
Provides-Extra: transformers
Requires-Dist: transformers>=4.44; extra == "transformers"
Dynamic: license-file
